LICENSE
MANIFEST.in
README.rst
setup.py
partial_date/__init__.py
partial_date/fields.py
partial_date/tests.py
r_django_partial_date.egg-info/PKG-INFO
r_django_partial_date.egg-info/SOURCES.txt
r_django_partial_date.egg-info/dependency_links.txt
r_django_partial_date.egg-info/requires.txt
r_django_partial_date.egg-info/top_level.txt