Metadata-Version: 1.1
Name: r-django-partial-date
Version: 1.3.1.1
Summary: Django custom model field for partial dates with the form YYYY, YYYY-MM, YYYY-MM-DD
Home-page: https://github.com/RamsesMartinez/r-django-partial-date
Author: Ramses Martinez
Author-email: ramses.mtz96@gmail.com
License: MIT
Keywords: fields,django,dates,partial
Platform: UNKNOWN
Classifier: Development Status :: 5 - Production/Stable
Classifier: Framework :: Django
Classifier: Intended Audience :: Developers
Classifier: License :: OSI Approved :: MIT License
Classifier: Programming Language :: Python :: 3.6
Classifier: Programming Language :: Python :: 3.7
